sistema_bancario_pcvcpaulo/__init__.py
sistema_bancario_pcvcpaulo/sistema_bancario.py
sistema_bancario_pcvcpaulo-0.0.1.dist-info/METADATA
sistema_bancario_pcvcpaulo-0.0.1.dist-info/WHEEL
sistema_bancario_pcvcpaulo-0.0.1.dist-info/entry_points.txt
sistema_bancario_pcvcpaulo-0.0.1.dist-info/top_level.txt
sistema_bancario_pcvcpaulo-0.0.1.dist-info/RECORD
