Metadata-Version: 2.4
Name: sistema_bancario_pcvcpaulo
Version: 0.0.1
Summary: Simula um sistema bancário.
Home-page: https://github.com/PCVCPAULO/project_SistemaBancario_Python
Author: PCVCPAULO
Author-email: pcvcpaulo@gmail.com
Keywords: banco financeiro simulador
Requires-Python: >=3.8
Dynamic: author
Dynamic: author-email
Dynamic: description
Dynamic: description-content-type
Dynamic: home-page
Dynamic: keywords
Dynamic: requires-python
Dynamic: summary
